medium_to_markdown/Parser.py
medium_to_markdown/__init__.py
medium_to_markdown_py-1.1.9.dist-info/LICENSE
medium_to_markdown_py-1.1.9.dist-info/METADATA
medium_to_markdown_py-1.1.9.dist-info/WHEEL
medium_to_markdown_py-1.1.9.dist-info/top_level.txt
medium_to_markdown_py-1.1.9.dist-info/RECORD
